ferrypick.py
ferrypick-0.1.dev2.dist-info/LICENSE
ferrypick-0.1.dev2.dist-info/METADATA
ferrypick-0.1.dev2.dist-info/WHEEL
ferrypick-0.1.dev2.dist-info/entry_points.txt
ferrypick-0.1.dev2.dist-info/top_level.txt
ferrypick-0.1.dev2.dist-info/RECORD
