Metadata-Version: 2.1
Name: ferrypick
Version: 0.1.dev2
Summary: Apply patches from Fedora dist git to different components.
Home-page: https://github.com/fedora-python/ferrypick
License: CC0
Keywords: fedora,git
Platform: UNKNOWN
Classifier: License :: CC0 1.0 Universal (CC0 1.0) Public Domain Dedication
Classifier: Programming Language :: Python :: 3
Classifier: Programming Language :: Python :: 3 :: Only
Classifier: Programming Language :: Python :: 3.8
Classifier: Programming Language :: Python :: 3.9
Classifier: Topic :: Software Development :: Version Control :: Git
Requires-Python: >=3.8
